{
    "name": "aui-diagram-builder",
    "builds": {
        "aui-available-field": {
            "jsfiles": [
                "js/aui-available-field.js"
            ]
        },
        "aui-diagram-builder-base": {
            "jsfiles": [
                "js/aui-diagram-builder-base.js"
            ]
        },

        "aui-diagram-builder-connector": {
            "jsfiles": [
                "js/aui-diagram-builder-connector.js"
            ]
        },

        "aui-diagram-builder-impl": {
            "jsfiles": [
                "js/aui-diagram-builder-impl.js"
            ]
        },

        "aui-diagram-node": {
            "jsfiles": [
                "js/aui-diagram-node.js"
            ]
        },

        "aui-diagram-node-manager-base": {
            "jsfiles": [
                "js/aui-diagram-node-manager-base.js"
            ]
        },

        "aui-field-support": {
            "jsfiles": [
                "js/aui-field-support.js"
            ]
        }
    }
}
